scod/__init__.py
scod/modules/__init__.py
scod/modules/client.py
scod/modules/exceptions.py
scod/modules/group.py
scod/modules/owner.py
scod/modules/profile.py
scod/modules/property.py
scod/modules/uploader.py
scod/modules/user.py
scod/modules/validators.py
scod/scod.py
scod-0.1.2.dist-info/METADATA
scod-0.1.2.dist-info/WHEEL
scod-0.1.2.dist-info/RECORD
