Metadata-Version: 2.1
Name: scod
Version: 0.1.2
Summary: This module is essential for preprocessing receipt images to improve visual quality and facilitate automatic analysis.
License: MIT
Keywords: api,scod brasil,scod
Author: Ricardo Castro
Author-email: srrenks@gmail.com
Requires-Python: >=3.8,<4.0
Classifier: License :: OSI Approved :: MIT License
Classifier: Programming Language :: Python :: 3
Classifier: Programming Language :: Python :: 3.8
Classifier: Programming Language :: Python :: 3.9
Classifier: Programming Language :: Python :: 3.10
Classifier: Programming Language :: Python :: 3.11
Classifier: Programming Language :: Python :: 3.12
Requires-Dist: requests (>=2.32.2,<3.0.0)
